aproxyrelay/__init__.py
aproxyrelay/agents.py
aproxyrelay/core.py
aproxyrelay/process.py
aproxyrelay/req.py
aproxyrelay/scrapers/__init__.py
aproxyrelay/scrapers/core.py
aproxyrelay/scrapers/parser.py
aproxyrelay/scrapers/parser_engagemintcreative.py
aproxyrelay/scrapers/parser_freeproxylist.py
aproxyrelay/scrapers/parser_geonode.py
aproxyrelay/scrapers/parser_gg_my_dev_app.py
aproxyrelay/scrapers/parser_lumiproxy.py
aproxyrelay/scrapers/parser_monosans_anonymous.py
aproxyrelay/scrapers/parser_multiproxy.py
aproxyrelay/scrapers/parser_murongpig_proxy_master_http.py
aproxyrelay/scrapers/parser_murongpig_proxy_master_socks4.py
aproxyrelay/scrapers/parser_murongpig_proxy_master_socks5.py
aproxyrelay/scrapers/parser_proxyscrape.py
aproxyrelay/scrapers/parser_proxyscrape_http.py
aproxyrelay/scrapers/parser_proxyscraper_com.py
aproxyrelay/scrapers/parser_proxyspace_socks5.py
aproxyrelay/scrapers/parser_roosterkid_openproxylist_socks4.py
aproxyrelay/scrapers/parser_roosterkid_openproxylist_socks5.py
aproxyrelay/scrapers/parser_socks_proxy.py
aproxyrelay/scrapers/parser_spys_de.py
aproxyrelay/scrapers/parser_spys_nl.py
aproxyrelay/scrapers/parser_spys_us.py
aproxyrelay/scrapers/parser_ssl_proxies.py
aproxyrelay/scrapers/parser_sunny9577_proxy_scraper.py
aproxyrelay/scrapers/parser_the_speed_http.py
aproxyrelay/scrapers/parser_the_speed_sock4.py
aproxyrelay/scrapers/parser_the_speed_sock5.py
aproxyrelay-1.152.1rc13091336186.dist-info/LICENSE
aproxyrelay-1.152.1rc13091336186.dist-info/METADATA
aproxyrelay-1.152.1rc13091336186.dist-info/WHEEL
aproxyrelay-1.152.1rc13091336186.dist-info/entry_points.txt
aproxyrelay-1.152.1rc13091336186.dist-info/top_level.txt
aproxyrelay-1.152.1rc13091336186.dist-info/RECORD
