Metadata-Version: 2.2
Name: aproxyrelay
Version: 1.152.1rc13091336186
Summary: A Proxy Relay, forwarding requests through different IP.
Home-page: https://github.com/my-dev-app/proxy-relay
Author: undeƒined
Author-email: my-dev.app@domainsbyproxy.com
License: GNU AGPLv3
License-File: LICENSE
Requires-Dist: aiohttp
Requires-Dist: aiohttp_socks
Requires-Dist: beautifulsoup4
Provides-Extra: dev
Requires-Dist: build; extra == "dev"
Requires-Dist: flake8-bugbear; extra == "dev"
Requires-Dist: pytest; extra == "dev"
Requires-Dist: pytest-asyncio; extra == "dev"
Requires-Dist: pytest-cov; extra == "dev"
Requires-Dist: pytest-sugar; extra == "dev"
Requires-Dist: pytest-xdist; extra == "dev"
Requires-Dist: setuptools; extra == "dev"
Requires-Dist: twine; extra == "dev"
Requires-Dist: wheel; extra == "dev"
Dynamic: author
Dynamic: author-email
Dynamic: description
Dynamic: description-content-type
Dynamic: home-page
Dynamic: license
Dynamic: provides-extra
Dynamic: requires-dist
Dynamic: summary
